bitlist/__init__.py
bitlist/bitlist.py
bitlist-2.0.0.dist-info/licenses/LICENSE
bitlist-2.0.0.dist-info/METADATA
bitlist-2.0.0.dist-info/WHEEL
bitlist-2.0.0.dist-info/top_level.txt
bitlist-2.0.0.dist-info/RECORD
